Metadata-Version: 1.1
Name: nb2xls
Version: 0.1.0
Summary: Export Jupyter notebook as an Excel xls file.
Home-page: https://github.com/ideonate/nb2xls
Author: ideonate
Author-email: dan@ideonate.com
License: MIT
Download-URL: https://github.com/ideonate/nb2xls/tarball/0.1.0
Keywords: jupyter,nbconvert
Platform: UNKNOWN
Classifier: Development Status :: 4 - Beta
Classifier: License :: OSI Approved :: MIT License
Classifier: Programming Language :: Python :: 3.5
Classifier: Programming Language :: Python :: 3.6
Classifier: Programming Language :: Python :: 3.7
